{"cameraMode":{"drawMode":0,"name":"Shaded","section":"Shading Mode"},"sceneLighting":true,"audioPlay":false,"sceneViewState":{"showFog":true,"showMaterialUpdate":false,"showSkybox":true,"showFlares":true,"showImageEffects":true,"showParticleSystems":true,"showVisualEffectGraphs":true,"m_FxEnabled":true},"in2DMode":false,"pivot":{"x":404.0,"y":120.10000610351563,"z":-151.0},"rotation":{"x":-0.03131714090704918,"y":-0.755366861820221,"z":0.031388845294713977,"w":-0.6550512909889221},"size":101.3199234008789,"orthographic":false}